pymercury/__init__.py
pymercury/alembicutils.py
pymercury/csvparser.py
pymercury/sautils.py
pymercury-0.0.4.dist-info/DESCRIPTION.rst
pymercury-0.0.4.dist-info/METADATA
pymercury-0.0.4.dist-info/RECORD
pymercury-0.0.4.dist-info/WHEEL
pymercury-0.0.4.dist-info/metadata.json
pymercury-0.0.4.dist-info/top_level.txt
