Metadata-Version: 2.0
Name: pymercury
Version: 0.0.4
Summary: Utilities for SQLAlchemy and Alembic
Home-page: https://github.com/akupara/pymercury
Author: Lei Sun
Author-email: leix.sun@qq.com
License: MIT
Platform: UNKNOWN
Classifier: Development Status :: 4 - Beta
Classifier: Environment :: Web Environment
Classifier: Intended Audience :: Developers
Classifier: License :: OSI Approved :: MIT License
Classifier: Operating System :: OS Independent
Classifier: Programming Language :: Python
Classifier: Programming Language :: Python :: 2
Classifier: Programming Language :: Python :: 2.7
Classifier: Topic :: Software Development :: Libraries :: Python Modules
Classifier: Natural Language :: English
Requires-Dist: SQLAlchemy (>=1.0.8)
Requires-Dist: alembic (>=0.8.3)
Requires-Dist: unicodecsv (>=0.14.1)
